wandb_export/__init__.py
wandb_export/export.py
wandb_export/init_config.py
wandb_export/utils_config.py
wandb_export/configs_wandb_export/__init__.py
wandb_export-1.0.dist-info/licenses/LICENSE
wandb_export-1.0.dist-info/METADATA
wandb_export-1.0.dist-info/WHEEL
wandb_export-1.0.dist-info/entry_points.txt
wandb_export-1.0.dist-info/top_level.txt
wandb_export-1.0.dist-info/RECORD
