Metadata-Version: 2.4
Name: wandb-export
Version: 1.0
Summary: A package to export runs from a WandB project to a local folder.
Home-page: https://github.com/tboulet/Wandb-Export
Author: Timothé Boulet
Author-email: timothe.boulet0@gmail.com
License: MIT
License-File: LICENSE
Dynamic: author
Dynamic: author-email
Dynamic: description
Dynamic: description-content-type
Dynamic: home-page
Dynamic: license
Dynamic: license-file
Dynamic: summary
